sphinx_debuginfo/__init__.py
sphinx_debuginfo/py.typed
sphinx_debuginfo-0.2.2.post1.dist-info/LICENSE
sphinx_debuginfo-0.2.2.post1.dist-info/METADATA
sphinx_debuginfo-0.2.2.post1.dist-info/WHEEL
sphinx_debuginfo-0.2.2.post1.dist-info/entry_points.txt
sphinx_debuginfo-0.2.2.post1.dist-info/RECORD
