Metadata-Version: 2.1
Name: sphinx-debuginfo
Version: 0.2.2.post1
Summary: A Sphinx extension to include debugging information in the output.
Author-email: Dominic Davis-Foster <dominic@davis-foster.co.uk>
License: MIT
Keywords: debug,sphinx,sphinx-extension
Home-page: https://github.com/sphinx-toolbox/sphinx-debuginfo
Project-URL: Issue Tracker, https://github.com/sphinx-toolbox/sphinx-debuginfo/issues
Project-URL: Source Code, https://github.com/sphinx-toolbox/sphinx-debuginfo
Platform: Windows
Platform: macOS
Platform: Linux
Classifier: Development Status :: 4 - Beta
Classifier: Framework :: Sphinx :: Extension
Classifier: Intended Audience :: Developers
Classifier: License :: OSI Approved :: MIT License
Classifier: Operating System :: OS Independent
Classifier: Programming Language :: Python
Classifier: Programming Language :: Python :: 3 :: Only
Classifier: Programming Language :: Python :: 3.6
Classifier: Programming Language :: Python :: 3.7
Classifier: Programming Language :: Python :: 3.8
Classifier: Programming Language :: Python :: 3.9
Classifier: Programming Language :: Python :: 3.10
Classifier: Programming Language :: Python :: 3.11
Classifier: Programming Language :: Python :: 3.12
Classifier: Programming Language :: Python :: Implementation :: CPython
Classifier: Programming Language :: Python :: Implementation :: PyPy
Classifier: Topic :: Documentation
Classifier: Topic :: Documentation :: Sphinx
Classifier: Topic :: Software Development :: Documentation
Classifier: Typing :: Typed
Requires-Python: >=3.6
Requires-Dist: domdf-python-tools>=3.2.2.post1
Requires-Dist: sphinx>=3.0.3
Requires-Dist: sphinx-jinja2-compat>=0.1.2
Requires-Dist: tabulate>=0.8.9
